odoo/addons/ssi_batch_project_assignment/README.rst
odoo/addons/ssi_batch_project_assignment/__init__.py
odoo/addons/ssi_batch_project_assignment/__manifest__.py
odoo/addons/ssi_batch_project_assignment/data/approval_template_data.xml
odoo/addons/ssi_batch_project_assignment/data/ir_sequence_data.xml
odoo/addons/ssi_batch_project_assignment/data/policy_template_data.xml
odoo/addons/ssi_batch_project_assignment/data/sequence_template_data.xml
odoo/addons/ssi_batch_project_assignment/i18n/ssi_batch_project_assignment.pot
odoo/addons/ssi_batch_project_assignment/models/__init__.py
odoo/addons/ssi_batch_project_assignment/models/project_assignment.py
odoo/addons/ssi_batch_project_assignment/models/project_batch_assignment.py
odoo/addons/ssi_batch_project_assignment/models/project_batch_assignment_assignee.py
odoo/addons/ssi_batch_project_assignment/security/ir.model.access.csv
odoo/addons/ssi_batch_project_assignment/security/ir_module_category_data.xml
odoo/addons/ssi_batch_project_assignment/security/ir_rule_data.xml
odoo/addons/ssi_batch_project_assignment/security/res_group_data.xml
odoo/addons/ssi_batch_project_assignment/static/description/icon.png
odoo/addons/ssi_batch_project_assignment/views/project_assignment_views.xml
odoo/addons/ssi_batch_project_assignment/views/project_batch_assignment_views.xml
odoo14_addon_ssi_batch_project_assignment-14.0.1.4.0.dist-info/METADATA
odoo14_addon_ssi_batch_project_assignment-14.0.1.4.0.dist-info/WHEEL
odoo14_addon_ssi_batch_project_assignment-14.0.1.4.0.dist-info/top_level.txt
odoo14_addon_ssi_batch_project_assignment-14.0.1.4.0.dist-info/RECORD
